dbdeclare/__init__.py
dbdeclare/controller.py
dbdeclare/data_structures/__init__.py
dbdeclare/data_structures/grant_on.py
dbdeclare/data_structures/grant_to.py
dbdeclare/data_structures/privileges.py
dbdeclare/entities/__init__.py
dbdeclare/entities/cluster_entity.py
dbdeclare/entities/database.py
dbdeclare/entities/database_content.py
dbdeclare/entities/database_entity.py
dbdeclare/entities/entity.py
dbdeclare/entities/role.py
dbdeclare/entities/schema.py
dbdeclare/exceptions.py
dbdeclare/mixins/__init__.py
dbdeclare/mixins/grantable.py
dbdeclare/mixins/sql.py
dbdeclare/py.typed
dbdeclare-0.0.1.dist-info/LICENSE
dbdeclare-0.0.1.dist-info/WHEEL
dbdeclare-0.0.1.dist-info/METADATA
dbdeclare-0.0.1.dist-info/RECORD
