Metadata-Version: 2.1
Name: dbdeclare
Version: 0.0.1
Summary: Declarative layer for your database.
Home-page: https://raaidarshad.github.io/dbdeclare/
License: MIT
Keywords: sql,sqlalchemy,postgres
Author: Raaid Arshad
Author-email: raaid@protonmail.com
Requires-Python: >=3.11.0,<4.0.0
Classifier: Development Status :: 3 - Alpha
Classifier: Intended Audience :: Developers
Classifier: Intended Audience :: Information Technology
Classifier: Intended Audience :: System Administrators
Classifier: License :: OSI Approved :: MIT License
Classifier: Operating System :: OS Independent
Classifier: Programming Language :: Python
Classifier: Programming Language :: Python :: 3
Classifier: Programming Language :: Python :: 3.11
Classifier: Programming Language :: Python :: 3
Classifier: Programming Language :: Python :: 3 :: Only
Classifier: Programming Language :: Python :: 3.11
Classifier: Topic :: Database
Classifier: Typing :: Typed
Requires-Dist: sqlalchemy (>=2.0.0,<3.0.0)
Project-URL: Documentation, https://raaidarshad.github.io/dbdeclare/
Project-URL: Repository, https://github.com/raaidarshad/dbdeclare
